odoo_s3_fs/__init__.py
odoo_s3_fs/odoo_s3_fs.py
odoo_s3_fs-1.3.0.dist-info/METADATA
odoo_s3_fs-1.3.0.dist-info/WHEEL
odoo_s3_fs-1.3.0.dist-info/top_level.txt
odoo_s3_fs-1.3.0.dist-info/RECORD
