Metadata-Version: 2.1
Name: odoo-s3-fs
Version: 1.3.0
Summary: Odoo S3 Filestore Wrapper
Home-page: https://gitlab.ndp-systemes.fr/python-libs/odoo_s3_fs
Author: Alexis Pasquier, NDP Systemes
Author-email: opensource@ndp-systemes.fr
License: GPLv3
Platform: UNKNOWN
Classifier: Programming Language :: Python :: 2.7
Classifier: Programming Language :: Python :: 3.6
Classifier: Programming Language :: Python :: 3.7
Classifier: Programming Language :: Python :: 3.8
Classifier: Programming Language :: Python :: 3.9
Classifier: Programming Language :: Python :: 3.10
Requires-Python: !=3.1.*,!=3.2.*,!=3.3.*,!=3.4.*,!=3.5.*,>=2.7
Requires-Dist: typing (==3.10.0.0) ; python_version <= "3"
Requires-Dist: minio (==6.0.*) ; python_version == "2.7"
Requires-Dist: minio (==7.1.1) ; python_version >= "3.6"
